{
  "header": {
    "id": "51",
    "slug": "record-keeping-quiz",
    "title": "Record keeping and documentation — scenario quiz"
  },
  "body": {
    "summary": "Test your judgement on everyday record-keeping situations — accurate, timely documentation protects service users and staff.",
    "text": {
      "id": 1,
      "type": "multiple_choice",
      "question": "What must always be recorded in care documentation?",
      "options": [
        "Opinions only",
        "Facts and accurate details",
        "Only serious incidents",
        "Only daily notes"
      ],
      "correctAnswer": "Facts and accurate details"
    }
  },
  "metadata": {
    "format": "scenario-quiz",
    "topicIDs": [
      "50"
    ],
    "themes": [
      "Record keeping and documentation",
      "Data protection and confidentiality",
      "Regulatory compliance",
      "Professional conduct and boundaries",
      "Communication"
    ]
  }
}
